smart_cacher/__init__.py
smart_cacher/google.py
smart_cacher-0.1.0.dist-info/LICENSE
smart_cacher-0.1.0.dist-info/WHEEL
smart_cacher-0.1.0.dist-info/METADATA
smart_cacher-0.1.0.dist-info/RECORD
