Metadata-Version: 2.1
Name: smart-cacher
Version: 0.1.0
Summary: 
Author: Sahand Johansen
Author-email: sahand.johansen@gmail.com
Requires-Python: >=3.10,<4.0
Classifier: Programming Language :: Python :: 3
Classifier: Programming Language :: Python :: 3.10
Classifier: Programming Language :: Python :: 3.11
Requires-Dist: google-cloud-storage (>=2.5.0,<3.0.0)
